README.md
setup.py
BrainGraphStudio/__init__.py
BrainGraphStudio/__main__.py
BrainGraphStudio/data.py
BrainGraphStudio/nni.py
BrainGraphStudio/utils.py
BrainGraphStudio.egg-info/PKG-INFO
BrainGraphStudio.egg-info/SOURCES.txt
BrainGraphStudio.egg-info/dependency_links.txt
BrainGraphStudio.egg-info/entry_points.txt
BrainGraphStudio.egg-info/requires.txt
BrainGraphStudio.egg-info/top_level.txt
BrainGraphStudio/BrainGB/__init__.py
BrainGraphStudio/BrainGB/src/__init__.py
BrainGraphStudio/BrainGB/src/dataset/__init__.py
BrainGraphStudio/BrainGB/src/dataset/base_transform.py
BrainGraphStudio/BrainGB/src/dataset/brain_data.py
BrainGraphStudio/BrainGB/src/dataset/brain_dataset.py
BrainGraphStudio/BrainGB/src/dataset/maskable_list.py
BrainGraphStudio/BrainGB/src/dataset/transforms.py
BrainGraphStudio/BrainGB/src/dataset/utils.py
BrainGraphStudio/BrainGB/src/dataset/abcd/__init__.py
BrainGraphStudio/BrainGB/src/dataset/abcd/load_abcd.py
BrainGraphStudio/BrainGB/src/models/__init__.py
BrainGraphStudio/BrainGB/src/models/brainnn.py
BrainGraphStudio/BrainGB/src/models/gat.py
BrainGraphStudio/BrainGB/src/models/gcn.py
BrainGraphStudio/BrainGB/src/models/losses.py
BrainGraphStudio/BrainGB/src/models/mlp.py
BrainGraphStudio/BrainGB/src/models/pna.py
BrainGraphStudio/BrainGB/src/utils/__init__.py
BrainGraphStudio/BrainGB/src/utils/bin_edges.py
BrainGraphStudio/BrainGB/src/utils/get_y.py
BrainGraphStudio/BrainGB/src/utils/mixup.py
BrainGraphStudio/gui/__init__.py
BrainGraphStudio/gui/pages.py
BrainGraphStudio/gui/utils.py
BrainGraphStudio/gui/ims/__init__.py
BrainGraphStudio/models/__init__.py
BrainGraphStudio/models/model.py
BrainGraphStudio/models/params.py
BrainGraphStudio/models/train.py
BrainGraphStudio/models/utils.py
BrainGraphStudio/models/brainGNN/__init__.py
BrainGraphStudio/models/brainGNN/braingnn.py
BrainGraphStudio/models/brainGNN/braingraphconv.py
BrainGraphStudio/models/brainGNN/brainmsgpassing.py
BrainGraphStudio/models/brainGNN/inits.py
BrainGraphStudio/models/brainGNN/loss.py
BrainGraphStudio/train/input_utils.py
BrainGraphStudio/train/train_brain_gb.py
BrainGraphStudio/train/train_brain_gnn.py
BrainGraphStudio/train/train_utils.py