Metadata-Version: 2.1
Name: BrainGraphStudio
Version: 0.1.4
Summary: A GUI-based toolkit for building, training, and optimizing graph neural networks for brain graph analysis
Home-page: https://github.com/berkyalcinkaya/BrainGraphStudio
Author: Berk Yalcinkaya
Author-email: berkyalcinkaya55@gmail.com
License: BSD
Classifier: Programming Language :: Python :: 3.9
Classifier: License :: OSI Approved :: BSD License
Classifier: Operating System :: OS Independent
Requires-Dist: numpy~=1.21.2
Requires-Dist: pandas~=1.2.3
Requires-Dist: scikit-learn~=1.0.2
Requires-Dist: networkx~=2.6.2
Requires-Dist: node2vec~=0.4.4
Requires-Dist: scipy~=1.7.3
Requires-Dist: nni~=2.4
Requires-Dist: PyQt5
Requires-Dist: matplotlib==3.8
Requires-Dist: tensorboardX
Provides-Extra: cpu
Requires-Dist: torch==1.8.1; extra == "cpu"
Requires-Dist: torchvision==0.9.1; extra == "cpu"
Requires-Dist: torchaudio==0.8.1; extra == "cpu"
Provides-Extra: gpu
Requires-Dist: torch==1.8.1+cu101; extra == "gpu"
Requires-Dist: torchvision==0.9.1+cu101; extra == "gpu"
Requires-Dist: torchaudio==0.8.1; extra == "gpu"
